LICENSE
arko/wrapper/__init__.py
arko/wrapper/_wrapper.py
arko_wrapper-0.4.2.dist-info/METADATA
arko_wrapper-0.4.2.dist-info/WHEEL
arko_wrapper-0.4.2.dist-info/licenses/LICENSE
arko_wrapper-0.4.2.dist-info/RECORD
