Metadata-Version: 2.1
Name: arko-wrapper
Version: 0.4.2
Summary: 给你的Python迭代器加上魔法
Author-Email: Arko <arko.space.cc@gmail.com>
Maintainer-Email: Karako <karakohear@gmail.com>
License: MIT License
Classifier: License :: OSI Approved :: MIT License
Classifier: Programming Language :: Python
Classifier: Programming Language :: Python :: 3
Classifier: Programming Language :: Python :: 3.7
Classifier: Programming Language :: Python :: 3.8
Classifier: Programming Language :: Python :: 3.9
Classifier: Programming Language :: Python :: 3.10
Classifier: Programming Language :: Python :: 3.11
Classifier: Programming Language :: Python :: 3.12
Classifier: Programming Language :: Python :: Implementation :: CPython
Project-URL: Homepage, https://github.com/ArkoClub/ArkoWrapper
Project-URL: Repository, https://github.com/ArkoClub/ArkoWrapper.git
Project-URL: Issues, https://github.com/ArkoClub/ArkoWrapper/issues
Requires-Python: >=3.12
Requires-Dist: typing-extensions>=4.12.2
Requires-Dist: more-itertools; extra == "more"
Provides-Extra: more
